setup.py
reuter_util/__init__.py
reuter_util/bgp.py
reuter_util/general.py
reuter_util.egg-info/PKG-INFO
reuter_util.egg-info/SOURCES.txt
reuter_util.egg-info/dependency_links.txt
reuter_util.egg-info/not-zip-safe
reuter_util.egg-info/requires.txt
reuter_util.egg-info/top_level.txt