Metadata-Version: 1.0
Name: reuter-util
Version: 0.1
Summary: Utility functions
Home-page: http://github.com/reuteran/reuter_util
Author: Andreas Reuter
Author-email: andreas.reuter@fu-berlin.de
License: MIT
Platform: UNKNOWN
